ecal/__init__.py
ecal/abstract_cache.py
ecal/abstract_fetcher.py
ecal/ecn_fetcher.py
ecal/runtime_cache.py
ecal/sqlite_cache.py
ecal-1.0.2.dist-info/LICENSE
ecal-1.0.2.dist-info/METADATA
ecal-1.0.2.dist-info/WHEEL
ecal-1.0.2.dist-info/top_level.txt
ecal-1.0.2.dist-info/RECORD
